{
	"Version": 3,
	"Meta": {
		"Duration": 2.9,
		"Fps": 30.0,
		"Loop": true,
		"AreBeziersRestricted": true,
		"CurveCount": 22,
		"TotalSegmentCount": 82,
		"TotalPointCount": 232,
		"UserDataCount": 0,
		"TotalUserDataSize": 0
	},
	"Curves": [
		{
			"Target": "Parameter",
			"Id": "ParamAngleX",
			"Segments": [
				0,
				0,
				1,
				0.333,
				0,
				0.667,
				0,
				1,
				0,
				1,
				1.444,
				0,
				1.889,
				0,
				2.333,
				0,
				0,
				2.9,
				0
			]
		},
		{
			"Target": "Parameter",
			"Id": "ParamAngleY",
			"Segments": [
				0,
				22,
				1,
				0.167,
				22,
				0.333,
				30,
				0.5,
				30,
				1,
				0.667,
				30,
				0.833,
				22,
				1,
				22,
				1,
				1.167,
				22,
				1.333,
				30,
				1.5,
				30,
				1,
				1.556,
				30,
				1.611,
				30,
				1.667,
				30,
				1,
				1.889,
				30,
				2.111,
				0,
				2.333,
				0,
				0,
				2.9,
				0
			]
		},
		{
			"Target": "Parameter",
			"Id": "ParamAngleZ",
			"Segments": [
				0,
				-17,
				1,
				0.167,
				-17,
				0.333,
				-30,
				0.5,
				-30,
				1,
				0.667,
				-30,
				0.833,
				-17,
				1,
				-17,
				1,
				1.167,
				-17,
				1.333,
				-30,
				1.5,
				-30,
				1,
				1.556,
				-30,
				1.611,
				-30,
				1.667,
				-30,
				1,
				1.889,
				-30,
				2.111,
				0,
				2.333,
				0,
				0,
				2.9,
				0
			]
		},
		{
			"Target": "Parameter",
			"Id": "ParamEyeLOpen",
			"Segments": [
				0,
				1,
				0,
				2.9,
				1
			]
		},
		{
			"Target": "Parameter",
			"Id": "ParamEyeROpen",
			"Segments": [
				0,
				1,
				0,
				2.9,
				1
			]
		},
		{
			"Target": "Parameter",
			"Id": "ParamEyeBallX",
			"Segments": [
				0,
				0,
				1,
				0.333,
				0,
				0.667,
				0,
				1,
				0,
				0,
				2.9,
				0
			]
		},
		{
			"Target": "Parameter",
			"Id": "ParamEyeBallY",
			"Segments": [
				0,
				1,
				1,
				0.333,
				1,
				0.667,
				1,
				1,
				1,
				0,
				2.9,
				1
			]
		},
		{
			"Target": "Parameter",
			"Id": "ParamBrowLAngle",
			"Segments": [
				0,
				0,
				0,
				2.9,
				0
			]
		},
		{
			"Target": "Parameter",
			"Id": "ParamBrowRAngle",
			"Segments": [
				0,
				0,
				0,
				2.9,
				0
			]
		},
		{
			"Target": "Parameter",
			"Id": "ParamArmL_Z",
			"Segments": [
				0,
				4,
				1,
				0.167,
				4,
				0.333,
				6,
				0.5,
				6,
				1,
				0.667,
				6,
				0.833,
				4,
				1,
				4,
				1,
				1.167,
				4,
				1.333,
				6,
				1.5,
				6,
				1,
				1.556,
				6,
				1.611,
				6,
				1.667,
				6,
				1,
				1.889,
				6,
				2.111,
				0,
				2.333,
				0,
				0,
				2.9,
				0
			]
		},
		{
			"Target": "Parameter",
			"Id": "ParamArmR_Z",
			"Segments": [
				0,
				30,
				1,
				0.167,
				30,
				0.333,
				20,
				0.5,
				20,
				1,
				0.667,
				20,
				0.833,
				30,
				1,
				30,
				1,
				1.167,
				30,
				1.333,
				20,
				1.5,
				20,
				1,
				1.556,
				20,
				1.611,
				20,
				1.667,
				20,
				1,
				1.889,
				20,
				2.111,
				0,
				2.333,
				0,
				0,
				2.9,
				0
			]
		},
		{
			"Target": "Parameter",
			"Id": "ParamCocktailTurn",
			"Segments": [
				0,
				-30,
				0,
				2.9,
				-30
			]
		},
		{
			"Target": "Parameter",
			"Id": "ParamCocktailPour",
			"Segments": [
				0,
				0,
				0,
				2.9,
				0
			]
		},
		{
			"Target": "Parameter",
			"Id": "ParamEyesNormal",
			"Segments": [
				0,
				0,
				1,
				0.333,
				0,
				0.667,
				0,
				1,
				0,
				1,
				1.222,
				0,
				1.444,
				0,
				1.667,
				0,
				1,
				1.678,
				0,
				1.689,
				1,
				1.7,
				1,
				0,
				2.9,
				1
			]
		},
		{
			"Target": "Parameter",
			"Id": "ParamEyesScared",
			"Segments": [
				0,
				0,
				1,
				0.333,
				0,
				0.667,
				0,
				1,
				0,
				0,
				2.9,
				0
			]
		},
		{
			"Target": "Parameter",
			"Id": "ParamEyesExcited",
			"Segments": [
				0,
				1,
				1,
				0.333,
				1,
				0.667,
				1,
				1,
				1,
				1,
				1.222,
				1,
				1.444,
				1,
				1.667,
				1,
				1,
				1.678,
				1,
				1.689,
				0,
				1.7,
				0,
				0,
				2.9,
				0
			]
		},
		{
			"Target": "Parameter",
			"Id": "ParamItemDrop",
			"Segments": [
				0,
				0,
				0,
				2.9,
				0
			]
		},
		{
			"Target": "Parameter",
			"Id": "ParamItemBack",
			"Segments": [
				0,
				0,
				0,
				2.9,
				0
			]
		},
		{
			"Target": "Parameter",
			"Id": "ParamDrink_X1",
			"Segments": [
				0,
				-0.988,
				1,
				0.178,
				-0.988,
				0.356,
				-2.005,
				0.533,
				-2.005,
				1,
				0.689,
				-2.005,
				0.844,
				-0.68,
				1,
				-0.68,
				1,
				1.167,
				-0.68,
				1.333,
				-2.031,
				1.5,
				-2.031,
				1,
				1.778,
				-2.031,
				2.056,
				0.341,
				2.333,
				0.341,
				1,
				2.444,
				0.341,
				2.556,
				-0.161,
				2.667,
				-0.161,
				1,
				2.744,
				-0.161,
				2.822,
				-0.046,
				2.9,
				0.023
			]
		},
		{
			"Target": "Parameter",
			"Id": "ParamDrink_X2",
			"Segments": [
				0,
				0.003,
				1,
				0.111,
				0.003,
				0.222,
				0.242,
				0.333,
				0.242,
				1,
				0.456,
				0.242,
				0.578,
				-0.52,
				0.7,
				-0.52,
				1,
				0.844,
				-0.52,
				0.989,
				0.59,
				1.133,
				0.59,
				1,
				1.278,
				0.59,
				1.422,
				-0.49,
				1.567,
				-0.49,
				1,
				1.667,
				-0.49,
				1.767,
				0.108,
				1.867,
				0.108,
				1,
				1.956,
				0.108,
				2.044,
				-0.235,
				2.133,
				-0.235,
				1,
				2.244,
				-0.235,
				2.356,
				0.473,
				2.467,
				0.473,
				1,
				2.578,
				0.473,
				2.689,
				-0.406,
				2.8,
				-0.406,
				1,
				2.833,
				-0.406,
				2.867,
				-0.355,
				2.9,
				-0.281
			]
		},
		{
			"Target": "Parameter",
			"Id": "ParamDrink_Y1",
			"Segments": [
				0,
				-0.991,
				1,
				0.111,
				-0.991,
				0.222,
				-2.072,
				0.333,
				-2.072,
				1,
				0.467,
				-2.072,
				0.6,
				-0.596,
				0.733,
				-0.596,
				1,
				0.9,
				-0.596,
				1.067,
				-2.077,
				1.233,
				-2.077,
				1,
				1.344,
				-2.077,
				1.456,
				-1.2,
				1.567,
				-1.2,
				1,
				1.611,
				-1.2,
				1.656,
				-1.399,
				1.7,
				-1.399,
				1,
				1.822,
				-1.399,
				1.944,
				0.479,
				2.067,
				0.479,
				1,
				2.178,
				0.479,
				2.289,
				-1.235,
				2.4,
				-1.235,
				1,
				2.511,
				-1.235,
				2.622,
				0.551,
				2.733,
				0.551,
				1,
				2.789,
				0.551,
				2.844,
				0.384,
				2.9,
				0.201
			]
		},
		{
			"Target": "Parameter",
			"Id": "ParamDrink_Y2",
			"Segments": [
				0,
				0.026,
				1,
				0.067,
				0.026,
				0.133,
				0.375,
				0.2,
				0.375,
				1,
				0.311,
				0.375,
				0.422,
				-0.75,
				0.533,
				-0.75,
				1,
				0.656,
				-0.75,
				0.778,
				0.847,
				0.9,
				0.847,
				1,
				1.044,
				0.847,
				1.189,
				-0.681,
				1.333,
				-0.681,
				1,
				1.456,
				-0.681,
				1.578,
				0.662,
				1.7,
				0.662,
				1,
				1.778,
				0.662,
				1.856,
				-0.83,
				1.933,
				-0.83,
				1,
				2.044,
				-0.83,
				2.156,
				1.124,
				2.267,
				1.124,
				1,
				2.367,
				1.124,
				2.467,
				-1.557,
				2.567,
				-1.557,
				1,
				2.678,
				-1.557,
				2.789,
				1.341,
				2.9,
				1.341
			]
		}
	]
}